radis/__init__.py
radis/__version__.txt
radis/default_radis.json
radis/api/__init__.py
radis/api/atomic_pf_api.py
radis/api/cache_files.py
radis/api/cdsdapi.py
radis/api/dbmanager.py
radis/api/exomolapi.py
radis/api/geisaapi.py
radis/api/hdf5.py
radis/api/hitempapi.py
radis/api/hitranapi.py
radis/api/kuruczapi.py
radis/api/nistapi.py
radis/api/tools.py
radis/db/NIST_Atomic_Ionization_Energies.txt
radis/db/__init__.py
radis/db/classes.py
radis/db/conventions.py
radis/db/degeneracies.py
radis/db/kuruczpartfn.txt
radis/db/molecules.py
radis/db/molparam.py
radis/db/molparam.txt
radis/db/molparams_extra.json
radis/db/pfTKurucz_values.txt
radis/db/references.py
radis/db/utils.py
radis/db/CO/__init__.py
radis/db/CO/molecules_data.json
radis/db/CO2/__init__.py
radis/db/CO2/gordon1966.json
radis/db/CO2/klarenaar2017.json
radis/db/CO2/molecules_data.json
radis/db/H2O/HITRANpage_january2025.htm
radis/gpu/gpu.py
radis/gpu/params.py
radis/gpu/structs.py
radis/gpu/vulkan/pyvkfft_base.py
radis/gpu/vulkan/pyvkfft_config.py
radis/gpu/vulkan/pyvkfft_vulkan.py
radis/gpu/vulkan/vulkan_compute_lib.py
radis/gpu/vulkan/bin/vkfft_vulkan.dll
radis/gpu/vulkan/bin/vkfft_vulkan.so
radis/gpu/vulkan/shaders/cmdApplyLineshapes.comp
radis/gpu/vulkan/shaders/cmdApplyLineshapes.spv
radis/gpu/vulkan/shaders/cmdFillLDM.comp
radis/gpu/vulkan/shaders/cmdFillLDM.spv
radis/io/__init__.py
radis/io/exomol.py
radis/io/geisa.py
radis/io/hitemp.py
radis/io/hitran.py
radis/io/kurucz.py
radis/io/nist.py
radis/io/npy.py
radis/io/query.py
radis/io/spec_hdf.py
radis/lbl/__init__.py
radis/lbl/bands.py
radis/lbl/base.py
radis/lbl/broadening.py
radis/lbl/calc.py
radis/lbl/factory.py
radis/lbl/labels.py
radis/lbl/loader.py
radis/lbl/overp.py
radis/levels/__init__.py
radis/levels/dunham.py
radis/levels/energies_co2.py
radis/levels/partfunc.py
radis/levels/partfunc_cdsd.py
radis/levels/vibrating_rotor.py
radis/los/__init__.py
radis/los/slabs.py
radis/misc/__init__.py
radis/misc/arrays.py
radis/misc/basics.py
radis-0.16.3.dist-info/licenses/LICENSE
radis-0.16.3.dist-info/METADATA
radis-0.16.3.dist-info/WHEEL
radis-0.16.3.dist-info/top_level.txt
radis-0.16.3.dist-info/RECORD
